README.md
setup.py
kuraudo_symbiosis/__init__.py
kuraudo_symbiosis/_inputs.py
kuraudo_symbiosis/_utilities.py
kuraudo_symbiosis/cluster.py
kuraudo_symbiosis/cluster_service_account.py
kuraudo_symbiosis/node_pool.py
kuraudo_symbiosis/outputs.py
kuraudo_symbiosis/provider.py
kuraudo_symbiosis/pulumi-plugin.json
kuraudo_symbiosis/py.typed
kuraudo_symbiosis/team_member.py
kuraudo_symbiosis.egg-info/PKG-INFO
kuraudo_symbiosis.egg-info/SOURCES.txt
kuraudo_symbiosis.egg-info/dependency_links.txt
kuraudo_symbiosis.egg-info/not-zip-safe
kuraudo_symbiosis.egg-info/requires.txt
kuraudo_symbiosis.egg-info/top_level.txt
kuraudo_symbiosis/config/__init__.py
kuraudo_symbiosis/config/vars.py